{"id":"re38vmy6nm5sjei20mmkvqi","title":"Ethernet Cables","desc":"CAT Cables","updated":1653231200716,"created":1653162391916,"custom":{},"fname":"networking.ethernet-cables","type":"note","vault":{"fsPath":"vault"},"contentHash":"dc6d997323da13e135e53d18323175e1","links":[],"anchors":{"general-info":{"type":"header","text":"General Info","value":"general-info","line":8,"column":0,"depth":2},"cable-catergories":{"type":"header","text":"Cable Catergories","value":"cable-catergories","line":12,"column":0,"depth":2}},"children":[],"parent":"qpngd6ap92mmahr4bh4gc47","data":{}}
